soa/__init__.py
soa/services.py
soa/directory/__init__.py
soa/directory/coap.py
soa/directory/directory.py
soa/directory/http.py
soa-0.2.0.dist-info/DESCRIPTION.rst
soa-0.2.0.dist-info/METADATA
soa-0.2.0.dist-info/RECORD
soa-0.2.0.dist-info/WHEEL
soa-0.2.0.dist-info/metadata.json
soa-0.2.0.dist-info/top_level.txt
