Metadata-Version: 2.0
Name: soa
Version: 0.2.0
Summary: Arrowhead core services
Home-page: https://github.com/eistec/arrowhead-python/
Author: Joakim Nohlgård
Author-email: joakim.nohlgard@eistec.se
License: Apache Software License
Download-URL: https://github.com/eistec/arrowhead-python/archive/v0.2.0.tar.gz
Keywords: arrowhead,soa,service,iot,coap
Platform: any
Classifier: Programming Language :: Python :: 3.4
Classifier: Programming Language :: Python :: 3.5
Classifier: Development Status :: 3 - Alpha
Classifier: Environment :: Web Environment
Classifier: Intended Audience :: Developers
Classifier: License :: OSI Approved :: Apache Software License
Classifier: Operating System :: OS Independent
Classifier: Topic :: Software Development :: Libraries :: Python Modules
Classifier: Topic :: Internet :: WWW/HTTP :: Dynamic Content
Classifier: Topic :: Internet :: Name Service (DNS)
Requires-Dist: LinkHeader (>=0.4.3)
Requires-Dist: aiocoap (>=0.2)
Requires-Dist: aiohttp (>=0.21)
Requires-Dist: attrs (>=16.0.0)
Requires-Dist: blitzdb (>=0.2.0)
Requires-Dist: six (>=1.6.1)
Provides-Extra: testing
Requires-Dist: pytest; extra == 'testing'
